anyradix/__init__.py
anyradix/anyradix.py
python_radix-0.1.1.dist-info/DESCRIPTION.rst
python_radix-0.1.1.dist-info/METADATA
python_radix-0.1.1.dist-info/metadata.json
python_radix-0.1.1.dist-info/RECORD
python_radix-0.1.1.dist-info/top_level.txt
python_radix-0.1.1.dist-info/WHEEL
radix/__init__.py
radix/radix.py
