Metadata-Version: 2.0
Name: python-radix
Version: 0.1.1
Summary: A tool for conversion numbers from one base to another
Home-page: https://github.com/valbub/python-radix
Author: valbub, yury-khrustalev
Author-email: UNKNOWN
License: MIT
Keywords: radix numbers
Platform: Any
Classifier: Development Status :: 3 - Alpha
Classifier: Intended Audience :: Developers
Classifier: License :: OSI Approved :: MIT License
Classifier: Programming Language :: Python :: 2
Classifier: Programming Language :: Python :: 2.7
Classifier: Programming Language :: Python :: 3
Classifier: Programming Language :: Python :: 3.4
